genie/libs/telemetry/__init__.py
genie/libs/telemetry/plugins/__init__.py
genie/libs/telemetry/plugins/alignmentcheck/__init__.py
genie/libs/telemetry/plugins/alignmentcheck/plugin.py
genie/libs/telemetry/plugins/alignmentcheck/iosxe/__init__.py
genie/libs/telemetry/plugins/alignmentcheck/iosxe/plugin.py
genie/libs/telemetry/plugins/alignmentcheck/iosxr/__init__.py
genie/libs/telemetry/plugins/alignmentcheck/iosxr/plugin.py
genie/libs/telemetry/plugins/alignmentcheck/nxos/__init__.py
genie/libs/telemetry/plugins/alignmentcheck/nxos/plugin.py
genie/libs/telemetry/plugins/cpucheck/__init__.py
genie/libs/telemetry/plugins/cpucheck/plugin.py
genie/libs/telemetry/plugins/cpucheck/iosxe/__init__.py
genie/libs/telemetry/plugins/cpucheck/iosxe/plugin.py
genie/libs/telemetry/plugins/cpucheck/iosxr/__init__.py
genie/libs/telemetry/plugins/cpucheck/iosxr/plugin.py
genie/libs/telemetry/plugins/cpucheck/nxos/__init__.py
genie/libs/telemetry/plugins/cpucheck/nxos/plugin.py
genie/libs/telemetry/plugins/crashdumps/__init__.py
genie/libs/telemetry/plugins/crashdumps/plugin.py
genie/libs/telemetry/plugins/crashdumps/iosxe/__init__.py
genie/libs/telemetry/plugins/crashdumps/iosxe/plugin.py
genie/libs/telemetry/plugins/crashdumps/iosxr/__init__.py
genie/libs/telemetry/plugins/crashdumps/iosxr/plugin.py
genie/libs/telemetry/plugins/crashdumps/nxos/__init__.py
genie/libs/telemetry/plugins/crashdumps/nxos/plugin.py
genie/libs/telemetry/plugins/libs/__init__.py
genie/libs/telemetry/plugins/libs/iosxe/__init__.py
genie/libs/telemetry/plugins/libs/iosxe/utils.py
genie/libs/telemetry/plugins/libs/iosxr/__init__.py
genie/libs/telemetry/plugins/libs/iosxr/utils.py
genie/libs/telemetry/plugins/libs/nxos/__init__.py
genie/libs/telemetry/plugins/libs/nxos/utils.py
genie/libs/telemetry/plugins/tracebackcheck/__init__.py
genie/libs/telemetry/plugins/tracebackcheck/plugin.py
genie/libs/telemetry/plugins/tracebackcheck/iosxe/__init__.py
genie/libs/telemetry/plugins/tracebackcheck/iosxe/plugin.py
genie.telemetry-25.9.dist-info/LICENSE
genie.telemetry-25.9.dist-info/METADATA
genie.telemetry-25.9.dist-info/WHEEL
genie.telemetry-25.9.dist-info/entry_points.txt
genie.telemetry-25.9.dist-info/top_level.txt
genie.telemetry-25.9.dist-info/RECORD
